CMakeLists.txt
CODE_OF_CONDUCT.md
CONTRIBUTING.md
LICENSE
MANIFEST.in
README.md
requirements.txt
setup.py
cmake/FindZMQ.cmake
cmake/FindZSTD.cmake
cpp/CMakeLists.txt
cpp/arguments.h
cpp/fifopipes.cpp
cpp/fifopipes.h
cpp/forkserver.cpp
cpp/forkserver.h
cpp/fsutils.cpp
cpp/fsutils.h
cpp/game.h
cpp/gamemultiplayer.cpp
cpp/gamesingleplayer.cpp
cpp/initialization.cpp
cpp/initialization.h
cpp/openbwprocess.cpp
cpp/openbwprocess.h
cpp/str.cpp
cpp/str.h
cpp/tc2lib.cpp
cpp/tc2main.cpp
cpp/utils.h
cpp/bindings/camelcase.h
cpp/bindings/pyclient.h
cpp/bindings/pyconstants.h
cpp/bindings/pyfeatures.h
cpp/bindings/pyreplayer.h
cpp/bindings/pystate.h
cpp/bindings/tc2lib.h
cpp/features/README.md
cpp/features/features.cpp
cpp/features/features.h
cpp/features/geometry.h
cpp/features/jitter.cpp
cpp/features/jitter.h
cpp/features/mapfeatures.cpp
cpp/features/tensor.h
cpp/features/tensortypes.h
cpp/features/types.h
cpp/features/unitsfeatures.cpp
cpp/features/unitsfeatures.h
scripts/tc2-setup
tc2/__init__.py
tc2/py.typed
tc2.egg-info/PKG-INFO
tc2.egg-info/SOURCES.txt
tc2.egg-info/dependency_links.txt
tc2.egg-info/not-zip-safe
tc2.egg-info/requires.txt
tc2.egg-info/top_level.txt
tc2/agents/__init__.py
tc2/agents/agents.py
tc2/constants/__init__.py
tc2/envs/__init__.py
tc2/envs/basic.py
tc2/envs/benchmark.py
tc2/envs/demo.py
tc2/envs/env.py
tc2/rules/__init__.py
tc2/rules/reward.py
tc2/tc2lib/__init__.pyi
tc2/tc2lib/Constants/__init__.pyi
tc2/tc2lib/Constants/bullettypes/__init__.pyi
tc2/tc2lib/Constants/colors/__init__.pyi
tc2/tc2lib/Constants/commands/__init__.pyi
tc2/tc2lib/Constants/dmgtypes/__init__.pyi
tc2/tc2lib/Constants/openbwcommandtypes/__init__.pyi
tc2/tc2lib/Constants/orders/__init__.pyi
tc2/tc2lib/Constants/races/__init__.pyi
tc2/tc2lib/Constants/techtypes/__init__.pyi
tc2/tc2lib/Constants/unitcommandtypes/__init__.pyi
tc2/tc2lib/Constants/unitsizes/__init__.pyi
tc2/tc2lib/Constants/unittypes/__init__.pyi
tc2/tc2lib/Constants/upgradetypes/__init__.pyi
tc2/tc2lib/Constants/usercommandtypes/__init__.pyi
tc2/tc2lib/Constants/weapontypes/__init__.pyi
tc2/tools/__init__.py
tc2/tools/command.py
tc2/tools/cvis.py
tc2/tools/spawn.py
