Metadata-Version: 2.1
Name: tc2
Version: 0.0.1594386854
Summary: A fast and easy way to run StarCraft: Brood War as a Gym environment.
Home-page: UNKNOWN
Author: Facebook AI Research
Author-email: oncall+torchcraft@xmail.facebook.com
License: MIT
Platform: UNKNOWN
Requires-Python: >=3.6
